agentmail/__init__.py
agentmail/api_keys/__init__.py
agentmail/api_keys/client.py
agentmail/api_keys/raw_client.py
agentmail/api_keys/types/__init__.py
agentmail/api_keys/types/api_key.py
agentmail/api_keys/types/api_key_id.py
agentmail/api_keys/types/create_api_key_request.py
agentmail/api_keys/types/create_api_key_response.py
agentmail/api_keys/types/created_at.py
agentmail/api_keys/types/list_api_keys_response.py
agentmail/api_keys/types/name.py
agentmail/api_keys/types/prefix.py
agentmail/attachments/__init__.py
agentmail/attachments/types/__init__.py
agentmail/attachments/types/attachment.py
agentmail/attachments/types/attachment_content_disposition.py
agentmail/attachments/types/attachment_content_id.py
agentmail/attachments/types/attachment_content_type.py
agentmail/attachments/types/attachment_filename.py
agentmail/attachments/types/attachment_id.py
agentmail/attachments/types/attachment_response.py
agentmail/attachments/types/attachment_size.py
agentmail/attachments/types/send_attachment.py
agentmail/client.py
agentmail/core/__init__.py
agentmail/core/api_error.py
agentmail/core/client_wrapper.py
agentmail/core/datetime_utils.py
agentmail/core/events.py
agentmail/core/file.py
agentmail/core/force_multipart.py
agentmail/core/http_client.py
agentmail/core/http_response.py
agentmail/core/http_sse/__init__.py
agentmail/core/http_sse/_api.py
agentmail/core/http_sse/_decoders.py
agentmail/core/http_sse/_exceptions.py
agentmail/core/http_sse/_models.py
agentmail/core/jsonable_encoder.py
agentmail/core/pydantic_utilities.py
agentmail/core/query_encoder.py
agentmail/core/remove_none_from_dict.py
agentmail/core/request_options.py
agentmail/core/serialization.py
agentmail/core/unchecked_base_model.py
agentmail/domains/__init__.py
agentmail/domains/client.py
agentmail/domains/raw_client.py
agentmail/domains/types/__init__.py
agentmail/domains/types/client_id.py
agentmail/domains/types/create_domain_request.py
agentmail/domains/types/domain.py
agentmail-0.2.9.dist-info/METADATA
agentmail-0.2.9.dist-info/WHEEL
agentmail-0.2.9.dist-info/RECORD
